{
  "header_home": "ఇల్లు",
  "header_about_us": "మా గురించి",
  "header_contact_us": "మమ్మల్ని సంప్రదించండి",
  "header_need_employees": "ఉద్యోగులు కావాలి",
  "header_need_job": "ఉద్యోగం కావాలి",
  "header_lang_english": "English",
  "header_lang_hindi": "हिन्दी",
  "header_lang_tamil": "தமிழ்",
  "header_lang_malayalam": "മലയാളം",
  "header_lang_kannada": "ಕನ್ನಡ",
  "header_lang_telugu": "తెలుగు",
  "header_lang_odia": "ଓଡ଼ିଆ",
  "header_lang_bengali": "বাংলা",
  "header_lang_marathi": "मराठी",
  "header_lang_gujarati": "ગુજરાતી",
  "home_hero_unlock_your": "అన్‌లాక్ మీ",
  "home_hero_dream_career": "డ్రీం కెరీర్",
  "home_hero_empower_statement": "కైగల్ వ్యక్తులు తమ నైపుణ్యాలు, అభిరుచులు మరియు ఆకాంక్షలతో సరిపోయే అవకాశాలతో ప్రతిభను సరిపోల్చడం ద్వారా వారి కెరీర్‌లో లక్ష్యాన్ని కనుగొనడానికి మరియు అభివృద్ధి చెందడానికి అధికారం ఇస్తుంది..",
  "home_hero_ready_to_get_started": "ప్రారంభించడానికి సిద్ధంగా ఉన్నారా?",
  "home_hero_download_app": "అనేక బ్లూ-కాలర్ ఉద్యోగ అవకాశాలను కనుగొనడానికి మరియు మీ కెరీర్‌ని కిక్‌స్టార్ట్ చేయడానికి ఇప్పుడే కైగల్ యాప్‌ను డౌన్‌లోడ్ చేసుకోండి!",
  "home_need_employee": "ఉద్యోగులు కావాలా?",
  "home_success_stats_success": "విజయం",
  "home_success_stats_stats": "గణాంకాలు",
  "home_success_stats_total_clients": "మొత్తం క్లయింట్లు",
  "home_success_stats_candidates": "అభ్యర్థులు",
  "home_success_stats_interviews": "ఇంటర్వ్యూలు",
  "home_why_choose_us": "మమ్మల్ని ఎందుకు ఎంచుకోవాలి?",
  "home_why_choose_us_easiest_way_find_job": "మీ తదుపరి ఉద్యోగాన్ని కనుగొనడానికి సులభమైన మార్గం",
  "home_why_choose_us_absolutely_free": "పూర్తిగా ఉచితం",
  "home_why_choose_us_find_jobs_no_fee": "రుసుము చెల్లించకుండా ఉద్యోగాలు కనుగొనండి.",
  "home_why_choose_us_jobs_come_to_you": "ఉద్యోగాలు మీకు వస్తాయి",
  "home_why_choose_us_job_opportunities_directly": "మేము సంబంధిత ఉద్యోగ అవకాశాలను మీకు నేరుగా అందిస్తాము.",
  "home_why_choose_us_easy_interaction": "సులభమైన పరస్పర చర్య",
  "home_why_choose_us_connect_offline": "ఆఫ్‌లైన్‌లో కూడా అప్రయత్నంగా కైగల్‌తో కనెక్ట్ అవ్వండి.",
  "home_why_choose_us_multiple_choices": "బహుళ ఎంపికలు",
  "home_why_choose_us_explore_variety_jobs": "ఒకేసారి వివిధ రకాల ఉద్యోగ ఎంపికలను అన్వేషించండి.",
  "home_why_choose_us_local_opportunities": "స్థానిక అవకాశాలు",
  "home_why_choose_us_convenient_jobs_near_home": "సౌలభ్యం కోసం మీ ఇంటికి సమీపంలో ఉద్యోగాలను కనుగొనండి.",
  "home_why_choose_us_open_to_all": "అందరికీ తెరవండి",
  "home_why_choose_us_anyone_find_job": "అనుభవం లేదా చదువుతో సంబంధం లేకుండా ఎవరైనా ఉద్యోగం పొందవచ్చు.",
  "home_ways_to_register_way_to": "మార్గాలు కు",
  "home_ways_to_register_register": "కైగల్‌లో నమోదు చేసుకోండి",
  "home_ways_to_register_missed_call": "మిస్డ్ కాల్ ఇవ్వండి",
  "home_ways_to_register_register_via_whatsapp": "వాట్సాప్ ద్వారా నమోదు చేసుకోండి",
  "home_ways_to_register_download_kaigal_app": "కైగల్ యాప్‌ను డౌన్‌లోడ్ చేసుకోండి",
  "home_ways_to_register_trusted_by_trusted": "విశ్వసించబడింది",
  "home_ways_to_register_trusted_by_by": "ద్వారా",
  "home_ways_to_register_trusted_top_companies": "నమ్మదగిన ఉద్యోగ నియామకాల కోసం అగ్రశ్రేణి కంపెనీలు మరియు లెక్కలేనన్ని కార్మికులు విశ్వసించారు.",
  "home_how_it_works": "ఇది ఎలా పని చేస్తుంది?",
  "home_how_it_works_find_jobs_steps": "మీ కోసం ఉత్తమ సరిపోలిక ఉద్యోగాలను కనుగొనడానికి 3 సాధారణ దశలు!",
  "home_how_it_works_step_1": "దశ 1",
  "home_how_it_works_register": "నమోదు చేసుకోండి",
  "home_how_it_works_sign_up_options_one": "మా మొబైల్ యాప్‌ని ఉపయోగించి సైన్ అప్ చేయండి,",
  "home_how_it_works_sign_up_options_two": "WhatsAppలో సందేశం పంపండి లేదా ప్రారంభించడానికి మాకు మిస్డ్ కాల్ ఇవ్వండి!",
  "home_how_it_works_step_2": "దశ 2",
  "home_how_it_works_provide_details": "వివరాలను అందించండి",
  "home_how_it_works_share_skills_experience_one": "మాకు చెప్పండి",
  "home_how_it_works_share_skills_experience_two": "మీ కీలక నైపుణ్యాలు, పని అనుభవం మరియు ప్రాధాన్య ఉద్యోగ పాత్రలు కాబట్టి మేము మిమ్మల్ని ఉత్తమ అవకాశాలతో కనెక్ట్ చేయగలము!",
  "home_how_it_works_step_3": "దశ 3",
  "home_how_it_works_receive_jobs": "ఉద్యోగాలు స్వీకరించండి",
  "home_how_it_works_get_job_matches_one": "పొందండి వ్యక్తిగతీకరించబడింది",
  "home_how_it_works_get_job_matches_two": "జాబ్ మ్యాచ్‌లు మీకు నేరుగా WhatsApp ద్వారా, IVR ద్వారా లేదా నేరుగా మొబైల్ యాప్‌లో అందించబడతాయి!",
  "home_how_it_works_step_4": "దశ 4",
  "home_how_it_works_choose_get_hired": "ఎంచుకోండి &  పొందండి అద్దెకు తీసుకున్నాడు",
  "home_how_it_works_select_job_apply_one": "ఉద్యోగాన్ని ఎంచుకోండి",
  "home_how_it_works_select_job_apply_two": "మీకు ఆసక్తిని కలిగిస్తుంది, మీ దరఖాస్తును సమర్పించండి మరియు మీ కొత్త పాత్రను ప్రారంభించడానికి సిద్ధంగా ఉండండి!",
  "home_how_it_works_get_started": "ప్రారంభించండి",
  "home_kaigal_presence": "కైగల్ ఉనికి",
  "home_kaigal_presence_connecting_jobs_across_india": "ఉత్తరం నుండి దక్షిణం వరకు, తూర్పు నుండి పడమర వరకు, కైగల్ భారతదేశం అంతటా ప్రజలను మరియు ఉద్యోగాలను కలుపుతోంది.",
  "home_kaigal_presence_nagaland": "నాగాలాండ్",
  "home_kaigal_presence_tamilnadu": "తమిళనాడు",
  "home_kaigal_presence_uttar_pradesh": "ఉత్తర ప్రదేశ్",
  "home_kaigal_presence_meghalaya": "మేఘాలయ",
  "home_kaigal_presence_sikkim": "సిక్కిం",
  "home_kaigal_presence_manipur": "మణిపూర్",
  "home_kaigal_presence_tripura": "త్రిపుర",
  "home_kaigal_presence_arunachal_pradesh": "అరుణాచల్ ప్రదేశ్",
  "home_kaigal_presence_assam": "అస్సాం",
  "home_kaigal_presence_mizoram": "మిజోరం",
  "home_partners": "భాగస్వాములు",
  "home_partners_do_good_partnership": "ఇతరులకు మంచి చేయండి, కైగల్‌కు సహాయం చేయండి మరియు సంపాదించండి",
  "home_partners_partner_info": "నేను కైగల్‌తో ఎలా భాగస్వామిగా ఉండగలను?",
  "home_partners_download_partner_app": "భాగస్వామి యాప్‌ను డౌన్‌లోడ్ చేయండి",
  "home_partners_setup_partner_app": "భాగస్వామ్య వనరులను యాక్సెస్ చేయడానికి కైగల్ పార్టనర్ యాప్‌ని డౌన్‌లోడ్ చేసి, సెటప్ చేయండి.",
  "home_partners_refer_candidates_clients": "అభ్యర్థులు మరియు ఖాతాదారులను చూడండి",
  "home_partners_refer_and_unlock": "అభ్యర్థులను అప్రయత్నంగా సూచించడానికి మరియు ప్రత్యేక భాగస్వామ్య ప్రయోజనాలను అన్‌లాక్ చేయడానికి కైగల్ పార్టనర్ యాప్‌ను డౌన్‌లోడ్ చేసి, సెటప్ చేయండి.",
  "home_partners_earn_rewards_refer": "సిఫార్సు కోసం రివార్డ్‌లను పొందండి",
  "home_partners_boost_your_earnings": "ఎక్కువ మంది వ్యక్తులను సూచించడం ద్వారా మీ ఆదాయాలను పెంచుకోండి మరియు విజయవంతమైన ఎంగేజ్‌మెంట్‌ల కోసం రివార్డ్‌లను పొందండి.",
  "home_partners_download": "డౌన్‌లోడ్ చేయండి",
  "home_partners_visit_site": "సైట్‌ని సందర్శించండి",
  "home_more_about_kaigal": "కైగల్ గురించి మరింత",
  "home_more_about_kaigal_welcome_message": "కైగల్‌కు స్వాగతం! మా కమ్యూనిటీని అన్వేషించండి మరియు మా వీడియోలలో మమ్మల్ని ప్రత్యేకంగా ఉంచే వాటిని కనుగొనండి.",
  "home_faq_section": "తరచుగా అడిగే ప్రశ్నలు",
  "home_faq_section_product_billing_info": "ఉత్పత్తి మరియు బిల్లింగ్ గురించి మీరు తెలుసుకోవలసిన ప్రతిదీ.",
  "home_faq_section_what_is_kaigal": "కైగల్ అంటే ఏమిటి?",
  "home_faq_section_what_is_kaigal_answer": "కైగల్ అనేది బ్లూ కాలర్ ఉద్యోగార్ధులను అద్దెకు తీసుకోవాలనుకునే కంపెనీలతో అనుసంధానించే వేదిక.",
  "home_faq_section_how_post_job": "నేను కైగల్‌లో నా ఉద్యోగ ఖాళీలను ఎలా పోస్ట్ చేయాలి?",
  "home_faq_section_how_post_job_answer": "కైగల్‌లో మీ ఉద్యోగ ఖాళీలను పోస్ట్ చేయడానికి, కైగల్ క్లయింట్ వెబ్‌పేజీకి వెళ్లి, 'రిజిస్టర్ ఆన్ కైగల్' విభాగానికి వెళ్లండి. సూచనలను అనుసరించండి మరియు మీ రిజిస్ట్రేషన్‌ను పూర్తి చేయడానికి మరియు మీ ఉద్యోగ జాబితాను సజావుగా పోస్ట్ చేయడానికి ఆ విభాగంలో అందించిన బటన్‌లను క్లిక్ చేయండి!",
  "home_faq_section_how_identify_candidates": "కైగల్ నా ఉద్యోగం కోసం అభ్యర్థులను ఎలా గుర్తిస్తుంది?",
  "home_faq_section_how_identify_candidates_answer": "కైగల్ స్మార్ట్ మ్యాచ్ మేకింగ్ సిస్టమ్ ద్వారా మీ ఉద్యోగం కోసం అభ్యర్థులను గుర్తిస్తుంది. మీరు ఉద్యోగాన్ని పోస్ట్ చేసిన తర్వాత, మా ప్లాట్‌ఫారమ్ అభ్యర్థులు వారి నైపుణ్యాలు, అనుభవం, స్థానం మరియు ఉద్యోగ ప్రాధాన్యతల ఆధారంగా ఫిల్టర్ చేస్తుంది. మీరు అత్యంత అనుకూలమైన అభ్యర్థులను త్వరగా మరియు సమర్ధవంతంగా పొందేలా మేము మా విస్తృతమైన ప్రతిభ డేటాబేస్ మరియు అధునాతన అల్గారిథమ్‌లను కూడా ఉపయోగిస్తాము.",
  "home_faq_section_improve_chances_employees": "ఉద్యోగులను పొందే అవకాశాలను నేను ఎలా మెరుగుపరచగలను?",
  "home_faq_section_improve_chances_employees_answer": "కైగల్‌లో మీ ఉద్యోగులను కనుగొనే అవకాశాలను మెరుగుపరచడానికి, పాత్ర, బాధ్యతలు మరియు అవసరమైన నైపుణ్యాలను హైలైట్ చేసే స్పష్టమైన మరియు వివరణాత్మక వివరణను సృష్టించండి. పెర్క్‌లు లేదా కెరీర్ వృద్ధి అవకాశాలు వంటి పోటీ ప్రయోజనాలను ఆఫర్ చేయండి మరియు మీ ఉద్యోగ పోస్ట్‌ను మరింత శోధించగలిగేలా చేయడానికి నిర్దిష్ట కీలకపదాలను చేర్చండి. దరఖాస్తుదారుల ఆసక్తిని కొనసాగించడానికి వెంటనే వారితో సన్నిహితంగా ఉండండి మరియు మీ ఉద్యోగ పోస్ట్ యొక్క దృశ్యమానతను పెంచడానికి కైగల్ ప్రచార సాధనాలను ఉపయోగించడాన్ని పరిగణించండి. బాగా వ్రాసిన మరియు ఆకర్షణీయమైన జాబితా సరైన ప్రతిభను సమర్థవంతంగా ఆకర్షించడంలో సహాయపడుతుంది!",
  "home_faq_section_check_job_status": "నా ఉద్యోగ ప్రారంభ స్థితిని నేను ఎలా తనిఖీ చేయగలను?",
  "home_faq_section_check_job_status_answer": "మీ ఉద్యోగ అవకాశాల స్థితిని తనిఖీ చేయడానికి, kaigaljobs.comకు లాగిన్ చేయండి లేదా Play స్టోర్ నుండి యాప్‌ను డౌన్‌లోడ్ చేయండి. అక్కడ నుండి, మీరు అప్లికేషన్‌లను ట్రాక్ చేయవచ్చు, అభ్యర్థి ప్రొఫైల్‌లను వీక్షించవచ్చు మరియు మీ ఉద్యోగ పోస్ట్ స్థితి గురించి అన్నీ ఒకే చోట నుండి తెలుసుకోవచ్చు!",
  "home_faq_section_troubleshoot_app": "కైగల్ యాప్‌ని ఉపయోగించడంలో నాకు సమస్య ఉంటే?",
  "home_faq_section_troubleshoot_app_answer": "కైగల్ యాప్‌ని ఉపయోగించడంలో మీకు ఏదైనా సమస్య ఎదురైతే, support@kaigal.comకి ఇమెయిల్ చేయడం ద్వారా సహాయం కోసం మీరు మా మద్దతు బృందాన్ని సంప్రదించవచ్చు. ప్రత్యామ్నాయంగా, మీరు ఏదైనా సమస్యను ఎదుర్కొంటున్నట్లయితే, కింది నంబర్‌కు కాల్ చేయడానికి సంకోచించకండి: [కైగల్ సపోర్ట్ నంబర్‌ను చొప్పించండి]. ఏవైనా సమస్యలను త్వరగా పరిష్కరించి, సున్నితమైన అనుభవాన్ని అందించడంలో మీకు సహాయపడటానికి మేము ఇక్కడ ఉన్నాము!",
  "footer_find_job_with_kaigal": "కైగల్‌తో ఉద్యోగం కనుగొనండి!",
  "footer_download_app_text": "యాప్‌ని డౌన్‌లోడ్ చేయండి",
  "footer_hire_right_candidate": "కైగల్‌తో సరైన అభ్యర్థిని నియమించుకోండి",
  "footer_post_job_free": "పోస్ట్ జాబ్ ఉచితంగా",
  "footer_resources": "వనరులు",
  "footer_terms_conditions": "నిబంధనలు మరియు షరతులు",
  "footer_faq": "తరచుగా అడిగే ప్రశ్నలు",
  "footer_need_employee": "ఉద్యోగులు కావాలా?",
  "footer_need_job": "ఉద్యోగం కావాలా?",
  "client_hero_can't_seem": "దొరకడం లేదు లేదా ఉంచు ది",
  "client_hero_right_employee": "సరైన ఉద్యోగి?",
  "client_hero_kaigal_helps": "అధునాతన సాంకేతిక పరిజ్ఞానాన్ని ఉపయోగించి నైపుణ్యం కలిగిన బ్లూ కాలర్ కార్మికులతో త్వరగా మరియు సమర్ధవంతంగా వాటిని కనెక్ట్ చేయడం ద్వారా అన్ని పరిమాణాల వ్యాపారాలు నియామక సవాళ్లను అధిగమించడంలో కైగల్ సహాయం చేస్తుంది.",
  "client_investor": "పెట్టుబడిదారులు",
  "client_why_choose_us_effortless_job": "అప్రయత్నంగా జాబ్ పోస్టింగ్",
  "client_why_choose_us_create_job": "మా యూజర్ ఫ్రెండ్లీ ప్లాట్‌ఫారమ్‌తో నిమిషాల్లో ఉద్యోగ జాబితాలను సృష్టించండి.",
  "client_why_choose_us_qualified_candidates": "అర్హత కలిగిన అభ్యర్థులు",
  "client_why_choose_us_attract_top": "మా నెట్‌వర్క్ మరియు అధునాతన మ్యాచింగ్‌తో అత్యుత్తమ ప్రతిభను ఆకర్షించండి.",
  "client_why_choose_us_transparent_pricing": "పారదర్శక ధర",
  "client_why_choose_us_enjoy_fixed": "దాచిన ఖర్చులు లేదా ఆశ్చర్యాలు లేకుండా స్థిర రుసుములను ఆస్వాదించండి.",
  "client_why_choose_us_smart_matching": "స్మార్ట్ సరిపోలిక",
  "client_why_choose_us_our_technology": "మా సాంకేతికత ప్రొఫైల్‌లు మరియు అవసరాల ఆధారంగా అభ్యర్థులకు సరిపోలుతుంది.",
  "client_why_choose_us_trusted_by_thousand": "వేల మంది విశ్వసించారు",
  "client_why_choose_us_join_thousands": "కైగల్‌తో విజయవంతంగా ఉపాధి పొందుతున్న వేలాది వ్యాపారాలలో చేరండి.",
  "client_services": "సేవలు",
  "client_placement": "ప్లేస్‌మెంట్స్",
  "client_we_will_find": "మేము ఇంటర్వ్యూలను కనుగొంటాము, షార్ట్‌లిస్ట్ చేస్తాము మరియు షెడ్యూల్ చేస్తాము. మీరు అభ్యర్థిని ఎన్నుకోండి.",
  "client_advertisements": "ప్రకటనలు",
  "client_we_will_provide": "మేము మీ ఉద్యోగాన్ని ప్రమోట్ చేస్తాము. అభ్యర్థులు మిమ్మల్ని నేరుగా సంప్రదిస్తారు.",
  "client_reach_out": "చేరుకోండి",
  "client_our_engine": "మా ఇంజిన్ అగ్రశ్రేణి అభ్యర్థులను కనుగొంటుంది మరియు వారి ప్రొఫైల్‌లను మీకు నేరుగా పంపుతుంది.",
  "client_profile_share": "ప్రొఫైల్ భాగస్వామ్యం",
  "client_find_top": "అగ్ర అభ్యర్థులను త్వరగా కనుగొనండి. సమర్థవంతమైన నియామకం కోసం మా ఇంజిన్ ప్రొఫైల్‌లను క్యూరేట్ చేస్తుంది.",
  "client_how_it_works_6_simple_steps": "6 బ్లూ కాలర్ వర్కర్లను నియమించుకోవడానికి సాధారణ దశలు !",
  "client_how_it_works_hr_team": "మేము మీ హెచ్‌ఆర్/ఎక్స్‌టెండెడ్ హెచ్‌ఆర్ టీమ్",
  "client_how_it_works_step_1": "దశ 1",
  "client_how_it_works_register": "నమోదు చేసుకోండి",
  "client_how_it_works_create_one": "మీ కంపెనీ ప్రొఫైల్‌ని సృష్టించండి మరియు ఉద్యోగాలను పోస్ట్ చేయడం ప్రారంభించండి.",
  "client_how_it_works_create_two": "మా వెబ్‌సైట్ లేదా Android యాప్‌లో త్వరిత మరియు సులభమైన నమోదు.",
  "client_how_it_works_step_2": "దశ 2",
  "client_how_it_works_post_job": "మీ ఉద్యోగాన్ని పోస్ట్ చేయండి",
  "client_how_it_works_add_essential_one": "ఉద్యోగ శీర్షిక, స్థానం, జీతం మరియు అవసరాలు వంటి ముఖ్యమైన వివరాలను జోడించండి.",
  "client_how_it_works_reach_wide_two": "అర్హత కలిగిన అభ్యర్థుల విస్తృత శ్రేణిని చేరుకోండి.",
  "client_how_it_works_step_3": "దశ 3",
  "client_how_it_works_choose_plan": "ఒక ప్రణాళికను ఎంచుకోండి",
  "client_how_it_works_select_package_one": "మీ బడ్జెట్‌కు సరిపోయే హైరింగ్ ప్యాకేజీని ఎంచుకోండి.",
  "client_how_it_works_transparent_pricing_two": "దాచిన రుసుములు లేకుండా పారదర్శక ధర.",
  "client_how_it_works_step_4": "దశ 4",
  "client_how_it_works_get_method": "సరిపోలండి",
  "client_how_it_works_our_advanced_one": "మా అధునాతన సాంకేతికత మీ ఉద్యోగానికి సరైన అభ్యర్థులను కనుగొంటుంది.",
  "client_how_it_works_fast_efficient_two": "వేగవంతమైన మరియు సమర్థవంతమైన సరిపోలిక ప్రక్రియ.",
  "client_how_it_works_step_5": "దశ 5",
  "client_how_it_works_review_candidates": "అభ్యర్థులను సమీక్షించండి",
  "client_how_it_works_see_our_one": "అర్హత పొందిన అభ్యర్థుల మా క్యూరేటెడ్ షార్ట్‌లిస్ట్‌ను చూడండి.",
  "client_how_it_works_see_our_two": "మేము కమ్యూనికేషన్ మరియు షెడ్యూల్‌ను నిర్వహిస్తాము.",
  "client_how_it_works_step_6": "దశ 6",
  "client_how_it_works_hire_team": "మీ కొత్త టీమ్ మెంబర్‌ని నియమించుకోండి",
  "client_how_it_works_pay_final_one": "విజయవంతమైన నియామకం తర్వాత మాత్రమే తుది రుసుమును చెల్లించండి.",
  "client_how_it_works_pay_final_two": "ప్రారంభం నుండి ముగింపు వరకు అవాంతరాలు లేని నియామక ప్రక్రియ.",
  "about_hero_our_story": "మా కథ",
  "about_hero_story_behind": "కార్మికులు మరియు యజమానులను కలిపే కైగల్ వెనుక కథ",
  "about_timeline_year_one": "జనవరి 2019",
  "about_timeline_year_one_content": "కైగల్ ఐడియా పుట్టింది",
  "about_timeline_year_two": "జూన్ 2019",
  "about_timeline_year_two_content": "MVP సిద్ధంగా ఉంది",
  "about_timeline_year_three": "సెప్టెంబర్ 2019",
  "about_timeline_year_three_content": "మొదటి కస్టమర్ సంపాదించారు",
  "about_timeline_year_four": "డిసెంబర్ 2019",
  "about_timeline_year_four_content": "కైగల్ నమోదు చేయబడింది",
  "about_timeline_year_five": "మార్చి 2020",
  "about_timeline_year_five_content": "మొదటి చెల్లింపు కస్టమర్",
  "about_timeline_year_six": "మే 2020",
  "about_timeline_year_six_content": "వెబ్‌సైట్ ప్రారంభించబడింది",
  "about_timeline_year_seven": "ఆగస్టు 2020",
  "about_timeline_year_seven_content": "StartupTN నుండి కైగల్ TANSEED 1.0ని గెలుచుకుంది",
  "about_timeline_year_eight": "నవంబర్ 2020",
  "about_timeline_year_eight_content": "ఉద్యోగార్ధుల కోసం మొబైల్ యాప్ ప్రారంభించబడింది",
  "about_timeline_year_nine": "ఫిబ్రవరి 2021",
  "about_timeline_year_nine_content": "కైగల్ అనేక జిల్లాలకు విస్తరిస్తుంది",
  "about_timeline_year_ten": "ఏప్రిల్ 2021",
  "about_timeline_year_ten_content": "ప్రతి నెలా కైగల్ ఆదాయం 1లీ దాటుతుంది",
  "about_timeline_year_eleven": "జూన్ 2021",
  "about_timeline_year_eleven_content": "కైగల్ TNIFMC నుండి పెట్టుబడిని పొందుతుంది",
  "about_timeline_year_tweleve": "సెప్టెంబర్ 2021",
  "about_timeline_year_tweleve_content": "యజమానుల కోసం మొబైల్/వెబ్ యాప్ ప్రారంభించబడింది",
  "about_timeline_year_thirteen": "డిసెంబర్ 2021",
  "about_timeline_year_thirteen_content": "కైగల్ తమిళనాడులోని అన్ని జిల్లాలకు విస్తరించింది",
  "about_timeline_year_fourteen": "మార్చి 2022",
  "about_timeline_year_fourteen_content": "వర్క్‌ఫ్లో ఆటోమేషన్ పూర్తయింది",
  "about_timeline_year_fifteen": "జూన్ 2022",
  "about_timeline_year_fifteen_content": "భాగస్వామి యాప్ ప్రారంభించబడింది",
  "about_timeline_year_sixteen": "సెప్టెంబర్ 2022",
  "about_timeline_year_sixteen_content": "కైగల్ తమిళనాడు వెలుపల అడుగు పెట్టింది",
  "about_meet_our_team": "మా బృందాన్ని కలవండి",
  "about_meet_our_team_one": "అంకితభావంతో కూడిన కైగల్ బృందాన్ని కలవండి-అభిమానం కలిగిన నిపుణుల బృందం",
  "about_meet_our_team_two": "సరైన ఉద్యోగాన్ని కనుగొనడంలో మరియు మీ కెరీర్ లక్ష్యాలను సాధించడంలో మీకు సహాయపడటానికి.",
  "about_meet_our_teammates_one": "బాలమురుగన్ సుందరరాజన్",
  "about_meet_our_teammates_one_details": "వ్యవస్థాపకుడు & CEO",
  "about_meet_our_teammates_two": "రవిన్ సోమి",
  "about_meet_our_teammates_two_details": "సహ వ్యవస్థాపకుడు & CTO",
  "about_meet_our_teammates_three": "సెంథిల్ మణికందన్",
  "about_meet_our_teammates_three_details": "సహ వ్యవస్థాపకుడు & CTO",
  "about_meet_our_teammates_four": "మధన్ శశికుమార్",
  "about_meet_our_teammates_four_details": "సహ వ్యవస్థాపకుడు & CTO",
  "about_meet_our_teammates_five": "దీప్తి రవిచంద్రన్",
  "about_meet_our_teammates_five_details": "సహ వ్యవస్థాపకుడు & CTO",
  "about_meet_our_teammates_six": "చందు మణికండ Attina",
  "about_meet_our_teammates_six_details": "సహ వ్యవస్థాపకుడు & CTO",
  "about_meet_our_teammates_seven": "pavithra రవి",
  "about_meet_our_teammates_seven_details": "సహ వ్యవస్థాపకుడు & CTO",
  "about_our_mission_and_vision": "మా",
  "about_our_mission_and_vision_mission": "మిషన్",
  "about_our_mission_and_vision_and": "మరియు",
  "about_our_mission_and_vision_vision": "విజన్",
  "about_our_mission_and_vision_m_v": "మిషన్ మరియు విజన్",
  "about_our_mission_and_vision_connecting": "2028 నాటికి 1 మిలియన్ ఉద్యోగాలను సృష్టించడానికి 10 మిలియన్ల ఉద్యోగార్ధులను 1 మిలియన్ ప్రొవైడర్‌లతో కనెక్ట్ చేస్తున్నాము. మేము పనిని సులభతరం చేస్తున్నాము మరియు అవకాశాలను అందుబాటులోకి తెస్తున్నాము.",
  "about_our_mission_and_vision_empowers": "కైగల్ వారి జీవితాలను మెరుగుపర్చడానికి సాధనాలు మరియు అవకాశాలతో వ్యక్తులకు శక్తినిస్తుంది, మెరుగైన భవిష్యత్తు కోసం సిద్ధంగా ఉన్నవారికి మద్దతు ఇస్తుంది.",
  "about_explore_our_gallery_explore_our": "మా అన్వేషించండి",
  "about_explore_our_gallery_gallery": "గ్యాలరీ",
  "tac_tac": "నిబంధనలు మరియు షరతులు/ గోప్యతా విధానం",
  "tac_by_using": "కైగల్ వెబ్‌సైట్ మరియు దాని సేవలను ఉపయోగించడం ద్వారా, మీరు మీ సమాచారాన్ని (మీ విద్యా నేపథ్యం, ​​మీ ఉద్యోగ నేపథ్యం, ​​మీ కంపెనీ సమాచారం, ఆర్థిక సమాచారం, గుర్తింపు, నేపథ్యం మరియు సాధారణంగా దీని నుండి ఉత్పన్నమయ్యే ఏదైనా ఇతర సమాచారాన్ని కలిగి ఉండవచ్చు) సేకరణ మరియు వినియోగానికి అంగీకరిస్తున్నారు. , ఈ విధానంలో వివరించిన విధంగా కైగల్ వెబ్‌సైట్ మరియు/లేదా సేవల నుండి సేకరించబడినది లేదా దానికి సంబంధించినది, అటువంటి సమాచారం ఇకపై “డేటా”గా సూచించబడుతుంది).",
  "tac_you_also": "మీకు ఉపాధి సమాచారాన్ని అందించడానికి లేదా మా సేవతో నేరుగా లేదా మూడవ పక్ష ప్లాట్‌ఫారమ్ ద్వారా మీకు సహాయం చేయడానికి Kaigal.com ఇమెయిల్, మొబైల్, SMS, టెలిగ్రామ్ లేదా WhatsApp ద్వారా మిమ్మల్ని సంప్రదించవచ్చని కూడా మీరు అంగీకరిస్తున్నారు.",
  "tac_if_we": "మేము మా గోప్యతా పద్ధతులను మార్చాలని నిర్ణయించుకుంటే, మేము ఆ మార్పులను ఈ గోప్యతా ప్రకటన, హోమ్ పేజీ మరియు మేము సముచితంగా భావించే ఇతర ప్రదేశాలకు పోస్ట్ చేస్తాము, తద్వారా మేము ఏ సమాచారాన్ని సేకరిస్తాము, దానిని ఎలా ఉపయోగిస్తాము మరియు ఏ పరిస్థితులలో మీరు తెలుసుకుంటారు, ఏదైనా ఉంటే, మేము దానిని బహిర్గతం చేస్తాము.",
  "tac_we_reserve": "ఈ గోప్యతా ప్రకటనను ఎప్పుడైనా సవరించే హక్కు మాకు ఉంది, కాబట్టి దయచేసి దీన్ని తరచుగా సమీక్షించండి. మేము మీ వ్యక్తిగతంగా గుర్తించదగిన సమాచారాన్ని ఉపయోగించే విధానాన్ని మార్చినట్లయితే, మేము మీకు ఇక్కడ తెలియజేస్తాము, ఇమెయిల్ ద్వారా లేదా మా హోమ్ పేజీలో నోటీసు ద్వారా.",
  "tac_we_care": "మీ గోప్యతను రక్షించడం గురించి మేము చాలా శ్రద్ధ వహిస్తాము. దయచేసి మీరు connect@kaigal.comకు ఏవైనా ప్రశ్నలు మరియు/లేదా వ్యాఖ్యలను పోస్ట్ చేయండి.",
  "tac_key_takeways": "కీలక టేకావేలు:",
  "tac_we_will_not": "మీ ముందస్తు అనుమతి లేకుండా మేము మీకు ఎలాంటి కమ్యూనికేషన్‌లను పంపము. మేము మీతో ఎప్పుడు మరియు ఎలా కమ్యూనికేట్ చేయాలో నియంత్రించే సామర్థ్యాన్ని మీరు కలిగి ఉంటారు.",
  "tac_we_use": "మేము మీ డేటాను Kaigal.com మరియు మీరు ఎంచుకున్న సేవకు సంబంధించిన దాని భాగస్వామి సేవా ప్రయోజనాల కోసం మాత్రమే ఉపయోగిస్తాము.",
  "tac_we_will_never": "మేము మీ సమ్మతి లేకుండా మీ సంప్రదింపు సమాచారాన్ని మరొక వినియోగదారుతో ఎప్పటికీ భాగస్వామ్యం చేయము.",
  "tac_we_will_employ": "మీరు అందించే డేటాను సురక్షితంగా ఉంచడానికి మేము సహేతుకమైన మరియు ప్రస్తుత ఇంటర్నెట్ భద్రతా పద్ధతులు, సాంకేతికతలు, రక్షణలు మరియు ప్రక్రియలను ఉపయోగిస్తాము.",
  "tac_data_that": "మేము సేకరించే డేటా:",
  "tac_job_seeker": "ఉద్యోగార్ధుల నమోదు సమాచారం",
  "tac_kaigal_collects": "ఉద్యోగార్ధుల నమోదు కోసం మీకు మరియు కైగల్ ప్రతినిధికి మధ్య టెలిఫోనిక్ ఇంటరాక్షన్ సమయంలో కైగల్ మీ నుండి వ్యక్తిగతంగా గుర్తించదగిన నిర్దిష్ట సమాచారాన్ని సేకరిస్తుంది. రిజిస్ట్రేషన్ సమయంలో మీరు సంప్రదింపు సమాచారాన్ని అందిస్తారు (ఫోన్ నంబర్, చిరునామా వంటివి). మీరు మాతో మీ ఖాతాను ధృవీకరించిన తర్వాత, మీ పేరు, నగరం, రాష్ట్రం, పని అనుభవం, విద్యా నేపథ్యం, ​​ధృవీకరణ మరియు సూచనలు వంటి మరింత వ్యక్తిగత సమాచారం కోసం మిమ్మల్ని అడుగుతారు. మా సేవలను ఉపయోగించడానికి మిమ్మల్ని అనుమతించడానికి మీ కైగల్ వర్కర్ ప్రొఫైల్‌ని రూపొందించడానికి మేము ఈ సమాచారాన్ని ఉపయోగిస్తాము.",
  "tac_you_have_option": "జనాభా సమాచారాన్ని (ఆదాయ స్థాయి, లింగం మరియు పుట్టిన తేదీ వంటివి) మాకు అందించే అవకాశం మీకు ఉంది; మేము ఈ సమాచారాన్ని సమర్పించమని మిమ్మల్ని ప్రోత్సహిస్తున్నాము, తద్వారా మేము మా సైట్‌లో మీకు మరింత వ్యక్తిగతీకరించిన అనుభవాన్ని అందించగలము.",
  "tac_if_you": "మీరు మమ్మల్ని సంప్రదించడానికి మా వెబ్‌సైట్‌లోని మా సంప్రదింపు పేజీని ఉపయోగించాలని ఎంచుకుంటే, మేము మీ పేరు, శీర్షిక, కంపెనీ నంబర్, ఇమెయిల్ చిరునామా మరియు కంపెనీ పేరును సేకరిస్తాము. మీ విచారణకు ప్రతిస్పందించడానికి మేము ఈ సమాచారాన్ని ఉపయోగిస్తాము.",
  "tac_client_info": "క్లయింట్ సమాచారం",
  "tac_to_use": "మా సేవలను ఉపయోగించడానికి, MSME క్లయింట్లు మీకు సంబంధించిన డేటాను అలాగే కంపెనీ పేరు, చిరునామా, CIN, GSTIN మొదలైన మీ కంపెనీ సమాచారాన్ని అందించడాన్ని ఎంచుకోవచ్చు. మా సేవలను మరింతగా ఉపయోగించుకోవడానికి మిమ్మల్ని అనుమతించడానికి మీ కైగల్ క్లయింట్ ప్రొఫైల్‌ను రూపొందించడానికి మేము ఈ సమాచారాన్ని ఉపయోగిస్తాము.",
  "tac_additional_information": "మా సేవలను ఉపయోగించడానికి, మీరు మీ గురించి అలాగే మీ ఉద్యోగం, విద్య, వృత్తిపరమైన మరియు ఇతర ఆధారాలకు సంబంధించిన అదనపు డేటాను అందించడాన్ని ఎంచుకోవచ్చు. గుర్తింపు దొంగతనం మరియు మోసం నుండి మిమ్మల్ని మరియు మా సిస్టమ్ యొక్క ఇతర వినియోగదారులను రక్షించడానికి, మీ గుర్తింపును ధృవీకరించడానికి ఉపయోగించే డేటాను గుర్తించమని మేము అడగవచ్చు. కైగల్ మీ వ్యక్తిగత వివరాలు, ఉద్యోగ వివరాలు, విద్య వివరాలు మొదలైన వాటితో సహా మీ సున్నితమైన డేటాను రక్షించడానికి జాగ్రత్తలు తీసుకుంటుంది, ఉదాహరణకు, గుప్తీకరణ యొక్క అదనపు పొర ద్వారా మరియు ప్రత్యేక సురక్షిత సౌకర్యాలలో డేటాను విభజించడం.",
  "tac_cookies": "కుక్కీలు",
  "tac_like_most": "చాలా వెబ్‌సైట్‌ల మాదిరిగానే, కైగల్ మీకు నిరంతర అనుభవాన్ని అందించడానికి మరియు మా సేవ ఎలా ఉపయోగించబడుతుందో రికార్డ్ చేయడానికి మీ కంప్యూటర్‌కు కుకీ ని పంపుతుంది. కుక్కీ అనేది మీ కంప్యూటర్‌లో ఉండే ఒక చిన్న డేటా ఫైల్, ఇది మీరు అదే కంప్యూటర్ మరియు వెబ్ బ్రౌజర్‌ని ఉపయోగించి మా సైట్‌కి తిరిగి వచ్చినప్పుడు మిమ్మల్ని వినియోగదారుగా గుర్తించడానికి మమ్మల్ని అనుమతిస్తుంది. మీరు ఉపయోగించిన బ్రౌజర్ రకం, మీ ఇంటర్నెట్ ప్రోటోకాల్ చిరునామా మరియు రోజు తేదీ మరియు సమయం వంటి సమాచారాన్ని మేము లాగ్ చేస్తాము. అటువంటి సమాచారం మిమ్మల్ని ప్రత్యేకంగా గుర్తించదు, కానీ వెబ్‌సైట్ నాణ్యత మెరుగుదల, ట్రాఫిక్ విశ్లేషణ లేదా ఇతర సారూప్య ప్రయోజనాల కోసం ఉపయోగపడుతుంది. మేము కుక్కీలలో నిల్వ చేసిన సమాచారాన్ని వ్యక్తిగతంగా గుర్తించదగిన సమాచారానికి లింక్ చేయము.",
  "tac_use_of": "మూడవ పక్షాల కుక్కీల ఉపయోగం మా గోప్యతా విధానం పరిధిలోకి రాదు. ఈ కుక్కీలపై మాకు యాక్సెస్ లేదా నియంత్రణ లేదు. మీరు మా సైట్‌ను నావిగేట్ చేయడాన్ని సులభతరం చేయడానికి ఈ మూడవ పక్షాలు సెషన్ ID కుక్కీలను ఉపయోగిస్తాయి.",
  "tac_information_usage": "సమాచార వినియోగం",
  "tac_kaigal": "నమోదు ప్రక్రియలో మీరు ఎంచుకున్న సేవతో మీకు సహాయం చేయడానికి కైగల్ సేకరించిన సమాచారాన్ని ఉపయోగిస్తుంది.",
  "tac_havE_option": "జనాభా సమాచారాన్ని (ఆదాయ స్థాయి, లింగం మరియు పుట్టిన తేదీ వంటివి) మాకు అందించే అవకాశం మీకు ఉంది; మేము ఈ సమాచారాన్ని సమర్పించమని మిమ్మల్ని ప్రోత్సహిస్తున్నాము, తద్వారా మేము మా సైట్‌లో మీకు మరింత వ్యక్తిగతీకరించిన అనుభవాన్ని అందించగలము.",
  "tac_choose_to_use": "మీరు మమ్మల్ని సంప్రదించడానికి మా వెబ్‌సైట్‌లోని మా సంప్రదింపు పేజీని ఉపయోగించాలని ఎంచుకుంటే, మేము మీ పేరు, శీర్షిక, కంపెనీ నంబర్, ఇమెయిల్ చిరునామా మరియు కంపెనీ పేరును సేకరిస్తాము. మీ విచారణకు ప్రతిస్పందించడానికి మేము ఈ సమాచారాన్ని ఉపయోగిస్తాము.",
  "tac_use_your_personal": "మేము మీ వ్యక్తిగత సమాచారాన్ని సేకరించినప్పుడు మేము పేర్కొన్న విధంగా ఉపయోగిస్తాము. మేము మీ డేటాను ఉపయోగించే కొన్ని మార్గాలలో ఇవి ఉన్నాయి:",
  "tac_to_provide": "మిమ్మల్ని సంప్రదించడానికి మరియు మీకు నవీకరణలను అందించే సామర్థ్యాన్ని అందించడానికి;",
  "tac_to_meet": "ఒప్పంద బాధ్యతలను నెరవేర్చడానికి;",
  "tac_provide_relation": "అనుకూలీకరించిన కంటెంట్‌ను ప్రదర్శించే సేవలతో సహా మీరు అభ్యర్థించిన సేవలను అందించడానికి లేదా వాటికి సంబంధించి;",
  "tac_we_will_not_release": "మా సేవల్లో భాగంగా ఏదైనా లావాదేవీని ప్రాసెస్ చేయడానికి అవసరమైనప్పుడు మినహా మేము మీ వ్యక్తిగతంగా గుర్తించదగిన సమాచారాన్ని మూడవ పక్షాలకు విడుదల చేయము మరియు అప్పుడు కూడా, మీ ఎక్స్‌ప్రెస్ అనుమతితో మాత్రమే;",
  "tac_to_conduct": "మా కస్టమర్‌లు మరియు తుది వినియోగదారులకు మెరుగైన సేవలను అందించడానికి సర్వేలను నిర్వహించడం. మీ భాగస్వామ్యం స్వచ్ఛందంగా ఉంటుంది;",
  "tac_you_may_receive": "మీరు ఎప్పటికప్పుడు డేటాను కలిగి ఉండే మీ ప్రొఫైల్‌ను భాగస్వామ్యం చేయడానికి ఆహ్వానాలు, సందేశాలు లేదా రిమైండర్‌లను స్వీకరించవచ్చు. ఈ సందేశాలు కైగల్ సేవలను ఉపయోగించే ఇతర వినియోగదారుల ద్వారా ప్రారంభించబడ్డాయి మరియు కైగల్ ద్వారా కాదు. కైగల్ ఎలాంటి ఆహ్వానాలు, సందేశాలు లేదా రిమైండర్‌లను ఆమోదించదు మరియు అలాంటి రిమైండర్‌లకు అనుగుణంగా భాగస్వామ్యం చేయబడిన సమాచారం, సందేశాలు లేదా నోటిఫికేషన్‌లు మీ స్వంత పూచీతో అటువంటి వినియోగదారులతో భాగస్వామ్యం చేయబడతాయి. మీరు పేర్కొన్న సమాచారాన్ని భాగస్వామ్యం చేయకూడదని ఎంచుకోవచ్చు మరియు/లేదా మీ ఖాతా సెట్టింగ్‌లను సర్దుబాటు చేయడం ద్వారా అటువంటి రిమైండర్‌లు, సందేశాలు మరియు ఆహ్వానాలను నిలిపివేయడాన్ని ఎంచుకోవచ్చు.",
  "tac_acknowledge": "వార్తాలేఖ, కొత్త మరియు సవరించిన లావాదేవీల కోసం కైగల్ మీకు నోటిఫికేషన్‌లను పంపవచ్చని మీరు అంగీకరిస్తున్నారు మరియు కొత్త ఉత్పత్తులు, సేవలు లేదా ఆసక్తికరమైన ఈవెంట్‌ల సమాచారంతో మీరు మా నుండి కాలానుగుణ ఇమెయిల్‌లు లేదా మెయిలింగ్‌లను కూడా స్వీకరించవచ్చని అంగీకరిస్తున్నారు. మీరు అలాంటి నోటిఫికేషన్‌లను స్వీకరించకూడదనుకుంటే, దయచేసి connect@kaigal.comకి ఇమెయిల్ చేయడం ద్వారా మాకు తెలియజేయండి.",
  "tac_customer_testimonials": "కస్టమర్ టెస్టిమోనియల్స్",
  "tac_we_post_customer": "మేము వ్యక్తిగతంగా గుర్తించదగిన సమాచారాన్ని కలిగి ఉండే కస్టమర్ టెస్టిమోనియల్‌లను మా వెబ్‌సైట్‌లో పోస్ట్ చేస్తాము. మేము వారి టెస్టిమోనియల్‌తో పాటు వారి పేరును పోస్ట్ చేయడానికి టెస్టిమోనియల్‌ను పోస్ట్ చేయడానికి ముందు ఇమెయిల్ ద్వారా కస్టమర్ సమ్మతిని పొందుతాము.",
  "tac_information_sharing": "సమాచార భాగస్వామ్యం",
  "tac_we_not_rent": "మేము మీ వ్యక్తిగత సమాచారాన్ని మార్కెటింగ్ ప్రయోజనాల కోసం మూడవ పక్షాలకు అద్దెకు ఇవ్వము లేదా విక్రయించము. మీ అనుమతి లేకుండా మేము మీ సమాచారాన్ని ఎప్పటికీ బహిర్గతం చేయము.",
  "tac_we_reserve_right": "ఈ గోప్యతా ప్రకటనను ఎప్పుడైనా సవరించే హక్కు మాకు ఉంది, కాబట్టి దయచేసి దీన్ని తరచుగా సమీక్షించండి. మేము మీ వ్యక్తిగతంగా గుర్తించదగిన సమాచారాన్ని ఉపయోగించే విధానాన్ని మార్చినట్లయితే, మేము మీకు ఇక్కడ తెలియజేస్తాము, ఇమెయిల్ ద్వారా లేదా మా హోమ్ పేజీలో నోటీసు ద్వారా.",
  "tac_we_collect": "చట్టవిరుద్ధమైన కార్యకలాపాలు, అనుమానిత మోసం, ఏదైనా వ్యక్తి యొక్క భౌతిక భద్రతకు సంభావ్య బెదిరింపులతో కూడిన పరిస్థితులు, మా ఉపయోగ నిబంధనల ఉల్లంఘనకు సంబంధించి దర్యాప్తు చేయడానికి, నిరోధించడానికి లేదా చర్య తీసుకోవడానికి మేము వ్యక్తిగత సమాచారాన్ని మరియు మాకు అందుబాటులో ఉన్న ఏదైనా అదనపు సమాచారాన్ని సేకరించి, భాగస్వామ్యం చేయవచ్చు. , లేదా చట్టం ప్రకారం అవసరం.",
  "tac_on_website": "మా వెబ్‌సైట్‌లో, బయటి / మూడవ పక్షం లేదా మూడవ పక్షం యొక్క వెబ్‌సైట్ లింక్‌ల ద్వారా హోస్ట్ చేయబడిన కంటెంట్ లేదా కార్యాచరణకు మీరు మళ్లించబడవచ్చు. ఆ వెబ్‌సైట్‌లలో పోస్ట్ చేసిన గోప్యతా విధానాలను సమీక్షించమని మేము మిమ్మల్ని ప్రోత్సహిస్తున్నాము. అటువంటి వెబ్‌సైట్ మీ గురించి ఏదైనా సమాచారాన్ని సేకరించినట్లయితే కైగల్ బాధ్యత వహించదు.",
  "tac_time_creating": "మీ గుర్తింపును ధృవీకరించిన తర్వాత మీ ప్రొఫైల్‌ని సృష్టించే సమయంలో, కైగల్ మీ కైగల్ ప్రొఫైల్‌ను ప్రైవేట్‌గా లేదా ఎంపిక చేసుకుని యాక్సెస్ చేయగల ఎంపికను మీకు అందిస్తుంది. మీరు మీ ప్రొఫైల్‌ను ప్రైవేట్‌గా కాన్ఫిగర్ చేసే సందర్భాల్లో, మీ ప్రొఫైల్‌ను భాగస్వామ్యం చేయడానికి మీరు ఎంచుకున్న వ్యక్తులకు మాత్రమే మేము ప్రాప్యతను అందిస్తాము.",
  "tac_permitted": "అటువంటి యాక్సెస్ కోసం మీ అభ్యర్థనను ఇతర వినియోగదారు ఆమోదించిన తర్వాత మీరు వారి ప్రొఫైల్‌లకు పరిమిత ప్రాప్యతను అనుమతించవచ్చు. మా గోప్యతా విధానం ప్రకారం, మీరు మరొక వినియోగదారు ప్రొఫైల్ డేటాను సమీక్షించడానికి అధికారిక అభ్యర్థనను చేయవలసి ఉంటుంది. అటువంటి అభ్యర్థన అటువంటి సమీక్ష అభ్యర్థించబడుతున్న ఉద్దేశ్యాన్ని ఖచ్చితంగా సూచించాలి.",
  "tac_granted": "అటువంటి డేటా యొక్క సమీక్ష కోసం అటువంటి వినియోగదారు నుండి స్పష్టమైన సమ్మతిని స్వీకరించిన తర్వాత మీరు మరొక వినియోగదారు ప్రొఫైల్ డేటాకు ప్రాప్యతను మంజూరు చేయవచ్చు. అతని/ఆమె ప్రొఫైల్‌కు యాక్సెస్‌ను మంజూరు చేసే వ్యక్తి అటువంటి యాక్సెస్‌ను అందించడానికి పూర్తిగా బాధ్యత వహిస్తాడు మరియు కైగల్ మధ్యవర్తిగా అటువంటి సమాచారాన్ని యాక్సెస్ చేయడానికి లేదా ఉపయోగించేందుకు బాధ్యత వహించదు. అయితే, ప్రొఫైల్‌ను షేర్ చేస్తున్న వినియోగదారుకు తెలియజేయబడిన ఉద్దేశిత ఉపయోగం కాకుండా మరే ఇతర ప్రయోజనం కోసం సమాచారాన్ని ఉపయోగించకూడదని మీరు ఇందుమూలంగా అంగీకరిస్తున్నారు. మీరు ఇతర వినియోగదారులకు అయాచిత వాణిజ్య సందేశాలను పంపకూడదు. మీరు గోప్యమైన సమాచారాన్ని ఫార్వార్డ్ చేయకూడదు లేదా మా ఎక్స్‌ప్రెస్ సమ్మతి మరియు వినియోగదారు యొక్క ఎక్స్‌ప్రెస్ సమ్మతి లేకుండా ఏ పద్ధతిలోనైనా పొందిన మరొక వినియోగదారు గురించి ఏదైనా విషయాన్ని ఏదైనా మూడవ పక్షానికి ఉపయోగించకూడదు.",
  "tac_third_parties": "కొంత డేటాను ప్రాసెస్ చేయడంలో మాకు సహాయం చేయడానికి మేము మూడవ పక్షాలను ఉపయోగించినప్పటికీ, అటువంటి మూడవ పక్షాలు మా గోప్యతా విధానాలు మరియు గోప్యత మరియు భద్రతా ప్రమాణాలు మరియు నిబంధనలకు అనుగుణంగా ఉండాలని మేము కోరుతున్నాము.",
  "tac_share_your_info": "మేము మీ సమాచారాన్ని పరిమిత పరిస్థితులలో మూడవ పక్షాలతో భాగస్వామ్యం చేయవచ్చు, చట్టపరమైన ప్రక్రియను అనుసరించడం, మోసం లేదా ఆసన్నమైన హానిని నిరోధించడం మరియు మా నెట్‌వర్క్ మరియు సేవల భద్రతను నిర్ధారించడం లేదా మద్దతు సేవలు, సమగ్ర విశ్లేషణ వంటి చట్టబద్ధమైన వ్యాపార ప్రయోజనాల కోసం, వ్యక్తిగతంగా గుర్తించలేని డేటా, ఖాతా పునరుద్ధరణ లేదా వర్తించే చట్టం ప్రకారం మేము డేటాను భాగస్వామ్యం చేయాల్సిన అవసరం ఉన్న చోట.",
  "tac_how_we_comply": "మేము మా విధానాలకు ఎలా కట్టుబడి ఉంటాము:",
  "tac_utilize": "మీ వ్యక్తిగత సమాచారాన్ని అనధికారిక యాక్సెస్, ఉపయోగం లేదా బహిర్గతం నుండి రక్షించడంలో సహాయపడటానికి మేము భద్రతా సాంకేతికతలు, విధానాలు మరియు సంస్థాగత చర్యల కలయికను ఉపయోగిస్తాము. విశ్వాసాన్ని పెంపొందించడానికి కైగల్‌ను ఉపయోగించడం గురించి మీరు నమ్మకంగా ఉండాలని మేము కోరుకుంటున్నాము మరియు మేము సేకరించే సమాచారాన్ని రక్షించడానికి మేము కట్టుబడి ఉన్నాము. మేము ఇంటర్నెట్‌లో వ్యక్తిగత సమాచారం, ఉద్యోగ వివరాలు, విద్య వివరాలు మొదలైన సున్నితమైన వ్యక్తిగత డేటాను బదిలీ చేసినప్పుడు, మేము దానిని ఎన్‌క్రిప్షన్ టెక్నాలజీని ఉపయోగించి రక్షిస్తాము.",
  "tac_no_company": "ఏ కంపెనీ సంపూర్ణ భద్రతకు హామీ ఇవ్వలేనప్పటికీ, మీరు మాకు అందించే వ్యక్తిగత సమాచారాన్ని రక్షించడంలో సహాయపడటానికి మేము తగిన పరిపాలనా, సాంకేతిక మరియు భౌతిక భద్రతా విధానాలను అమలు చేసాము. అనధికార ప్రాప్యతను నిరోధించడానికి, డేటా ఖచ్చితత్వాన్ని నిర్వహించడానికి మరియు సమాచారం యొక్క సరైన వినియోగాన్ని నిర్ధారించడానికి, మేము సహేతుకమైన మరియు ప్రస్తుత ఇంటర్నెట్ భద్రతా పద్ధతులు, సాంకేతికతలు మరియు రక్షణ ప్రక్రియలను ఉపయోగిస్తాము. మేము మీ వ్యక్తిగత సమాచారాన్ని రక్షించడానికి ప్రయత్నిస్తున్నప్పుడు, మీరు ప్రసారం చేసే సమాచారం యొక్క భద్రతను మేము నిర్ధారించలేము.",
  "tac_we_recommend": "మీరు ఇంటర్నెట్‌లో ఉన్నప్పుడు మీ వ్యక్తిగత సమాచారాన్ని రక్షించుకోవడంలో ప్రతి జాగ్రత్తలు తీసుకోవాలని మేము మీకు సిఫార్సు చేస్తున్నాము. ఉదాహరణకు, మీ పాస్‌వర్డ్‌లను తరచుగా మార్చుకోండి, సురక్షితమైన బ్రౌజర్ మరియు ఇలాంటి వాటిని ఉపయోగించండి.",
  "tac_privacy_audits": "గోప్యతా తనిఖీలు",
  "tac_we_conduct": "మేము క్రమానుగతంగా గోప్యత మరియు డేటా భద్రతా తనిఖీలను నిర్వహిస్తాము. ఈ ఆడిట్‌లు సమస్యలను ముందుగానే గుర్తించడంలో మాకు సహాయపడతాయి. మేము స్వతంత్ర సంస్థ ద్వారా స్వతంత్ర వృత్తిపరమైన మరియు సాంకేతిక సమీక్షను కూడా నిర్వహిస్తాము.",
  "tac_referral_program": "రెఫరల్ ప్రోగ్రామ్/ ప్రీమియం జాబ్ సీకర్ ప్రోగ్రామ్",
  "tac_choose_referral": "మీరు మా సైట్ గురించి స్నేహితుడికి చెప్పడానికి మా రెఫరల్ సేవను ఉపయోగించాలని ఎంచుకుంటే, మేము మీ స్నేహితుడి ఫోన్ నంబర్ కోసం మిమ్మల్ని అడుగుతాము. మేము మీ స్నేహితుడికి స్వయంచాలకంగా SMS/WhatsAppని పంపుతాము, అతనిని లేదా ఆమెను మాకు మిస్డ్ కాల్ ఇవ్వమని లేదా వారి వివరాలను నమోదు చేసుకోవడానికి ఫోన్ ద్వారా కాల్ చేయమని ఆహ్వానిస్తాము. ఈ వన్-టైమ్ SMS పంపడం మరియు మా రిఫరల్ ప్రోగ్రామ్ యొక్క విజయాన్ని ట్రాక్ చేయడం కోసం మాత్రమే కైగల్ ఈ సమాచారాన్ని నిల్వ చేస్తుంది.",
  "tac_friend_contact": "మీ స్నేహితుడు మమ్మల్ని connect@kaigal.comలో సంప్రదించవచ్చు లేదా 89809 12345కి కాల్ చేసి మా డేటాబేస్ నుండి ఈ సమాచారాన్ని తీసివేయమని అభ్యర్థించవచ్చు.",
  "tac_agree_paying": "Kaigal.com యొక్క ప్రీమియం జాబ్ సీకర్ ప్రోగ్రామ్‌కు అంగీకరించడం మరియు చెల్లించడం ద్వారా, మీరు ఉద్యోగంలో చేరకపోతే Kaigal.com లేదా దాని అనుబంధ సంస్థలను బాధ్యులను చేయకూడదని మీరు అంగీకరిస్తున్నారు. Kaigal.com మీ ప్రొఫైల్‌కు సరిపోయే ఉద్యోగాలను సిఫార్సు చేస్తుందని మీరు అంగీకరిస్తున్నారు మరియు సంబంధిత ఉద్యోగ ఇంటర్వ్యూలకు హాజరు కావడానికి మరియు ఉద్యోగంలో విజయవంతంగా ల్యాండ్ అయ్యే అవకాశం ఉంది. Kaigal.com ప్రీమియం జాబ్ సీకర్ ప్రోగ్రామ్ ఒక వ్యక్తికి ఉద్యోగంలో చేరడంలో సహాయపడుతుందని వాగ్దానం చేయలేదు. Kaigal.com ప్రీమియం జాబ్ సీకర్ ప్రోగ్రామ్ అభ్యర్థులకు మరింత శ్రద్ధను అందించవచ్చు మరియు వారికి మరిన్ని ఉద్యోగ అవకాశాలను అందించవచ్చు.",
  "tac_your_choice": "మీ ఎంపికలు",
  "tac_we_offer": "సహేతుకంగా సాధ్యమైనప్పుడల్లా మేము వ్యక్తిగత సమాచారాన్ని అడిగినప్పుడు మేము మీకు ఎంపికలను అందిస్తాము. మీరు మాకు వ్యక్తిగత సమాచారాన్ని అందించడానికి నిరాకరించవచ్చు మరియు/లేదా మీ బ్రౌజర్‌లో కుక్కీలను తిరస్కరించవచ్చు, అయినప్పటికీ మా కొన్ని లక్షణాలు లేదా సేవలు ఫలితంగా సరిగ్గా పని చేయకపోవచ్చు.",
  "tac_amending_correcting": "వ్యక్తిగతంగా గుర్తించదగిన సమాచారాన్ని సవరించడం లేదా సరిదిద్దడం:",
  "tac_personality": "మీ వ్యక్తిగతంగా గుర్తించదగిన సమాచారం మారితే, లేదా మీరు ఇకపై మా సేవను కోరుకోనట్లయితే, మీరు మా సభ్యుని సమాచార పేజీలో మార్పు చేయడం ద్వారా లేదా మా కస్టమర్ సపోర్ట్‌ని connect@kaigal.comలో ఇమెయిల్ చేయడం ద్వారా లేదా టెలిఫోన్ ద్వారా మమ్మల్ని సంప్రదించడం ద్వారా దాన్ని సరిదిద్దవచ్చు లేదా సవరించవచ్చు. దిగువ జాబితా చేయబడిన సంప్రదింపు సమాచారం వద్ద పోస్టల్ మెయిల్. యాక్సెస్ చేయాలన్న మీ అభ్యర్థనకు మేము 30 రోజులలోపు ప్రతిస్పందిస్తాము.",
  "tac_questions": "ప్రశ్నలు లేదా వ్యాఖ్యలు",
  "tac_if_questions": "మీకు ఈ గోప్యతా విధానం గురించి ప్రశ్నలు లేదా వ్యాఖ్యలు ఉంటే, దయచేసి connect@kaigal.comకు ఇమెయిల్ చేయండి."
}
