{
    "about_us": "અમારા વિશે",
    "services": "સેવા",
    "solutions": "ઉકેલ",
    "gallery": "ગેલેરી",
    "faq": "વારંવાર પૂછાતા પ્રશ્નો",
    "need_candidates": "ઉમેદવારોની જરૂર છે?",
    "unlock_dream_career": "તમારા સપનાનો કરિયર અનલૉક કરો",
    "empower_statement": "કૈગલ વ્યક્તિઓને તેમની કૌશલ્ય, રસ અને ઇચ્છાઓ સાથે મેળ ખાતા તકો સાથે મેચ કરી, તેમના કારકિર્દી જીવનમાં પ્રગતિ કરવાનું સક્ષમ બનાવે છે.",
    "ready_to_get_started": "શરૂ કરવા માટે તૈયાર છો?",
    "download_app": "કૈગલ એપ્લિકેશન ડાઉનલોડ કરો અને અનેક બ્લૂ-કોલર નોકરી તકો શોધો!",
    "problem_statement": "અમે બે મોટા મુદ્દાઓ જોયા...",
    "partners": "ભાગીદારો",
    "why_choose_us": "અમને કેમ પસંદ કરો",
    "easiest_way_find_job": "તમારી આગલી નોકરી શોધવાનો સહેલો માર્ગ",
    "absolutely_free": "પૂરેપૂરી મફત",
    "jobs_come_to_you": "નૌકરીઓ તમારી પાસે આવે છે",
    "easy_interaction": "સરળ સંવાદ",
    "multiple_choices": "અનેક વિકલ્પો",
    "local_opportunities": "સ્થાનિક તકો",
    "open_to_all": "બધા માટે ખુલ્લું",
    "placements": "પ્લેસમેન્ટ",
    "advertisements": "જાહેરાતો",
    "reach_out": "સંપર્ક કરો",
    "how_it_works": "તે કેવી રીતે કામ કરે છે?",
    "steps_to_hire": "બ્લૂ-કોલર વર્કર્સને ભરતી કરવા માટે 6 સરળ પગલાં!",
    "current_challenges": "હાલના પડકારો",
    "team_kaigal_answer": "તમારા નોકરી શોધવા માટેના પડકારો માટે કૈગલ ટીમનો જવાબ:",
    "faq_section": "વારંવાર પૂછાતા પ્રશ્નો"
}
